PenPen-0.1.1b1.dist-info/DESCRIPTION.rst
PenPen-0.1.1b1.dist-info/METADATA
PenPen-0.1.1b1.dist-info/RECORD
PenPen-0.1.1b1.dist-info/WHEEL
PenPen-0.1.1b1.dist-info/entry_points.txt
PenPen-0.1.1b1.dist-info/metadata.json
PenPen-0.1.1b1.dist-info/top_level.txt
penpen/__init__.py
penpen/audio.py
penpen/core.py
penpen/fileUtils.py
penpen/penpen.py
penpen/rss.py
tests/__init__.py
