Metadata-Version: 2.0
Name: PenPen
Version: 0.1.1b1
Summary: Audio podcasting suite.
Home-page: https://github.com/ryanmeasel/PenPen
Author: Ryan Measel
Author-email: ryanmeasel@gmail.com
License: MIT
Platform: UNKNOWN
Classifier: Development Status :: 4 - Beta
Classifier: Intended Audience :: Information Technology
Classifier: Topic :: Utilities
Classifier: License :: OSI Approved :: MIT License
Classifier: Programming Language :: Python :: 2
Classifier: Programming Language :: Python :: 2.6
Classifier: Programming Language :: Python :: 2.7
Requires-Dist: mutagen (==1.33.2)
